paycomet/__init__.py
paycomet/apps.py
paycomet/forms.py
paycomet/payment.py
paycomet/services.py
paycomet/views.py
paycomet/templates/paycomet/payment_form.html
django_paycomet-1.0.0.dist-info/LICENSE
django_paycomet-1.0.0.dist-info/METADATA
django_paycomet-1.0.0.dist-info/WHEEL
django_paycomet-1.0.0.dist-info/top_level.txt
django_paycomet-1.0.0.dist-info/RECORD
