Metadata-Version: 2.1
Name: django-paycomet
Version: 1.0.0
Summary: PAYCOMET payment tools for Django
Home-page: https://github.com/semicolom/django-paycomet
Author: Toni Colom
Author-email: toni@semicolom.com
License: UNKNOWN
Platform: UNKNOWN
Classifier: Environment :: Web Environment
Classifier: Framework :: Django
Classifier: Framework :: Django :: 2.0
Classifier: Intended Audience :: Developers
Classifier: Operating System :: OS Independent
Classifier: Programming Language :: Python
Classifier: Programming Language :: Python :: 3.6
Classifier: Topic :: Internet :: WWW/HTTP
Classifier: Topic :: Internet :: WWW/HTTP :: Dynamic Content
Requires-Dist: pycrypto
Requires-Dist: zeep
